{
  "fluentMethods": true,
  "clientRootFolder": "",
  "relationships": [],
  "fields": [
    {
      "fieldName": "ma",
      "fieldType": "String",
      "fieldValidateRules": ["required", "unique"]
    },
    {
      "fieldName": "ten",
      "fieldType": "String",
      "fieldValidateRules": ["required"]
    }
  ],
  "dto": "mapstruct",
  "searchEngine": "elasticsearch",
  "service": "serviceImpl",
  "entityTableName": "dm_cqbh",
  "databaseType": "mongodb",
  "readOnly": false,
  "jpaMetamodelFiltering": false,
  "pagination": "pagination"
}
